OrderFusion/OrderFusion.py
OrderFusion/__init__.py
OrderFusion/data.py
OrderFusion/evaluation.py
OrderFusion/model.py
orderfusion-0.1.3.dist-info/METADATA
orderfusion-0.1.3.dist-info/WHEEL
orderfusion-0.1.3.dist-info/top_level.txt
orderfusion-0.1.3.dist-info/RECORD
