Metadata-Version: 2.4
Name: OrderFusion
Version: 0.1.3
Summary: Tutorial for the paper: OrderFusion Encoding Orderbook for End-to-End Probabilistic Intraday Electricity Price Forecasting
Home-page: https://huggingface.co/RunyaoYu
Author: Runyao Yu
Author-email: runyao.yu@tudelft.nl
License: MIT
Requires-Python: >=3.10,<3.12
Requires-Dist: Pillow==10.4.0
Requires-Dist: imageio==2.26.0
Requires-Dist: ipython==8.10.0
Requires-Dist: joblib==1.4.2
Requires-Dist: matplotlib==3.7.0
Requires-Dist: natsort==8.4.0
Requires-Dist: numpy==1.26.4
Requires-Dist: pandas==2.2.2
Requires-Dist: scikit-learn==1.5.2
Requires-Dist: tensorflow==2.16.2
Requires-Dist: tqdm==4.66.5
Dynamic: author
Dynamic: author-email
Dynamic: home-page
Dynamic: license
Dynamic: requires-dist
Dynamic: requires-python
Dynamic: summary
